algodojo/__init__.py
algodojo/ib.py
algodojo/base/__init__.py
algodojo/base/auth.py
algodojo/base/report.py
algodojo-0.3.4.dist-info/LICENSE.txt
algodojo-0.3.4.dist-info/METADATA
algodojo-0.3.4.dist-info/WHEEL
algodojo-0.3.4.dist-info/top_level.txt
algodojo-0.3.4.dist-info/RECORD
