Metadata-Version: 2.1
Name: algodojo
Version: 0.3.4
Summary: A automatic trading application of package
Author-email: AlgoDojo team <slin@dojotechs.com>
License: By using AlgoDojo (we, us, our) services (website, product, forums) you agree to the following terms of use.
Keywords: quant,quantitative,investment,trading,algotrading
Classifier: Programming Language :: Python :: 3
Classifier: Operating System :: OS Independent
License-File: LICENSE.txt
Requires-Dist: ibapi
Requires-Dist: python-socketio
Requires-Dist: requests
Requires-Dist: websocket-client
Requires-Dist: pandas
Requires-Dist: quantstats
Requires-Dist: matplotlib
